misho_cli/__init__.py
misho_cli/common.py
misho_cli/config.py
misho_cli/date_or_weekday.py
misho_cli/job_cli.py
misho_cli/reservation_calendar_cli.py
misho_cli/reserve_id.py
misho_cli-0.1.6.dist-info/METADATA
misho_cli-0.1.6.dist-info/WHEEL
misho_cli-0.1.6.dist-info/entry_points.txt
misho_cli-0.1.6.dist-info/RECORD
