Metadata-Version: 2.4
Name: misho-cli
Version: 0.1.6
Summary: Add your description here
Author-email: Ivo Petkovic <ivo.petkovic@gmail.com>
Requires-Python: >=3.12
Requires-Dist: misho-api
Requires-Dist: misho-client
Requires-Dist: pydantic>=2.11.7
Requires-Dist: rich>=14.0.0
Requires-Dist: typer>=0.16.0
